CHANGES.txt
README.txt
setup.py
jarn/__init__.py
jarn.checkinterval.egg-info/PKG-INFO
jarn.checkinterval.egg-info/SOURCES.txt
jarn.checkinterval.egg-info/dependency_links.txt
jarn.checkinterval.egg-info/entry_points.txt
jarn.checkinterval.egg-info/namespace_packages.txt
jarn.checkinterval.egg-info/not-zip-safe
jarn.checkinterval.egg-info/requires.txt
jarn.checkinterval.egg-info/top_level.txt
jarn/checkinterval/__init__.py
jarn/checkinterval/checkinterval.py