Metadata-Version: 1.0
Name: jarn.checkinterval
Version: 1.0
Summary: Compute optimal interpreter check interval for Zope
Home-page: http://www.jarn.com/
Author: Jarn AS
Author-email: info@jarn.com
License: BSD
Keywords: python zope interpreter check interval
Platform: UNKNOWN
Classifier: Framework :: Plone
Classifier: Framework :: Zope2
Classifier: Programming Language :: Python
